commit_format/__init__.py
commit_format/commit_format.py
commit_format-0.2.3.dist-info/licenses/LICENSE
commit_format-0.2.3.dist-info/METADATA
commit_format-0.2.3.dist-info/WHEEL
commit_format-0.2.3.dist-info/entry_points.txt
commit_format-0.2.3.dist-info/top_level.txt
commit_format-0.2.3.dist-info/RECORD
