Metadata-Version: 2.4
Name: commit_format
Version: 0.2.3
Summary: A tool to check git commit messages format
Author-email: Alex Fabre <m.alexfabre@gmail.com>
License: MIT License
Project-URL: Homepage, https://github.com/AlexFabre/commit-format
Project-URL: Issues, https://github.com/AlexFabre/commit-format/issues
Classifier: Programming Language :: Python :: 3
Classifier: Operating System :: OS Independent
Requires-Python: >=3.10
License-File: LICENSE
Requires-Dist: codespell
Dynamic: license-file
